odoo/addons/stock_location_lockdown/README.rst
odoo/addons/stock_location_lockdown/__init__.py
odoo/addons/stock_location_lockdown/__manifest__.py
odoo/addons/stock_location_lockdown/i18n/es.po
odoo/addons/stock_location_lockdown/i18n/fr.po
odoo/addons/stock_location_lockdown/i18n/it.po
odoo/addons/stock_location_lockdown/i18n/pt.po
odoo/addons/stock_location_lockdown/i18n/stock_location_lockdown.pot
odoo/addons/stock_location_lockdown/i18n/zh_CN.po
odoo/addons/stock_location_lockdown/models/__init__.py
odoo/addons/stock_location_lockdown/models/stock_location.py
odoo/addons/stock_location_lockdown/models/stock_quant.py
odoo/addons/stock_location_lockdown/readme/CONTRIBUTORS.md
odoo/addons/stock_location_lockdown/readme/DESCRIPTION.md
odoo/addons/stock_location_lockdown/readme/USAGE.md
odoo/addons/stock_location_lockdown/static/description/icon.png
odoo/addons/stock_location_lockdown/static/description/index.html
odoo/addons/stock_location_lockdown/tests/__init__.py
odoo/addons/stock_location_lockdown/tests/test_block_stock_location_entrance.py
odoo/addons/stock_location_lockdown/views/stock_location.xml
odoo_addon_stock_location_lockdown-18.0.1.0.0.2.dist-info/METADATA
odoo_addon_stock_location_lockdown-18.0.1.0.0.2.dist-info/WHEEL
odoo_addon_stock_location_lockdown-18.0.1.0.0.2.dist-info/top_level.txt
odoo_addon_stock_location_lockdown-18.0.1.0.0.2.dist-info/RECORD
